setup.cfg
setup.py
quadkey/__init__.py
quadkey/tile_system.py
quadkey/util.py
quadkey.egg-info/PKG-INFO
quadkey.egg-info/SOURCES.txt
quadkey.egg-info/dependency_links.txt
quadkey.egg-info/top_level.txt