Metadata-Version: 1.0
Name: quadkey
Version: 0.0.5
Summary: Python Implementation for Geospatial Quadkeys
Home-page: https://github.com/buckheroux/QuadKey
Author: Buck Heroux
Author-email: UNKNOWN
License: UNKNOWN
Platform: UNKNOWN
